[
  {
    "cat": "Áudio",
    "nome": "Senbenbao X55 Fones De Ouvido TWS Sleep Fone Sem Fio Bluetooth Display Led Hifi Estéreo Cancelamento De Ruído Esportivo",
    "preco": "12,51",
    "imagem": "https://cf.shopee.com.br/file/sg-11134201-7rdxs-mcanyyol3y009d",
    "link": "https://s.shopee.com.br/5fn3FRgyHk"
  },
  {
    "cat": "Áudio",
    "nome": "Compre 1 E Ganhe 1 Fone De Ouvido Sem Fio Bluetooth Único À Prova D'água Fones Bateria Longa Escritório Negócios Com Mic",
    "preco": "9,55",
    "imagem": "https://cf.shopee.com.br/file/sg-11134301-7rbni-m5y2k7sxyxzr3b",
    "link": "https://s.shopee.com.br/5q6TRkgKwn"
  },
  {
    "cat": "Áudio",
    "nome": "E6S Fones De Ouvido TWS Sem Fio Bluetooth 5.0 Display LED 9D Stero Fone Redução Ruído",
    "preco": "12,04",
    "imagem": "https://cf.shopee.com.br/file/d0031fa50a607ddaa7a90ec977893c58",
    "link": "https://s.shopee.com.br/5LACqpiExi"
  },
  {
    "cat": "Áudio",
    "nome": "Pro 4 Fones De Ouvido TWS Sem Fio Bluetooth Bateria Longa Duração Leve Portátil Com Caso Carregamento Correndo Dormir",
    "preco": "10,72",
    "imagem": "https://cf.shopee.com.br/file/sg-11134201-7rdvp-mcanw6gzu0d783",
    "link": "https://s.shopee.com.br/5VTd38hbcl"
  },
  {
    "cat": "Carregamento",
    "nome": "Cabo USB 3A LED Glow 1M-De Carregamento De Luz Fluida Luminosa Para Micro E Tipo C , Dados Rápido",
    "preco": "5,41",
    "imagem": "https://cf.shopee.com.br/file/sg-11134201-823o9-mp4luu5jpzpp6a",
    "link": "https://s.shopee.com.br/3ViYfT2Lho"
  },
  {
    "cat": "Carregamento",
    "nome": "Carregador rápido de 120W 67W com 6A USB C cabo 1M para Mi Turbo Charge Turbo Power Cabo USB + Cabo Tipo C",
    "preco": "19,90",
    "imagem": "https://cf.shopee.com.br/file/sg-11134201-7rdwm-mcqg8gq4duyo5b",
    "link": "https://s.shopee.com.br/3LP8TA2z2n"
  },
  {
    "cat": "Carregamento",
    "nome": "Carregador De Chaveiro Portátil | 1500mAh Ultra-Compacto Mini Pacote De Bateria Carregamento Rápido",
    "preco": "13,99",
    "imagem": "https://cf.shopee.com.br/file/sg-11134201-7rbn0-lozfabuz0tmm4b",
    "link": "https://s.shopee.com.br/3qLP45151u"
  },
  {
    "cat": "Carregamento",
    "nome": "Xiaomi 120W Carregador De Carregamento Cabo Ultra Rápido Tipo-C GaN Telefone USB QC 3.0 Adaptador De Para iPhone Samsung",
    "preco": "19,59",
    "imagem": "https://cf.shopee.com.br/file/sg-11134201-825b0-mqgzs0ecn5kxa8",
    "link": "https://s.shopee.com.br/3g1yrm1iMt"
  },
  {
    "cat": "Carregamento",
    "nome": "Carregador Portátil Indução para iPhone/Android Magsafe Sem fio Bateria Carga 5000mAH/10000mah",
    "preco": "26,98",
    "imagem": "https://cf.shopee.com.br/file/br-11134207-81z1k-mgaidmamo35sb3",
    "link": "https://s.shopee.com.br/8pk51GvFEC"
  },
  {
    "cat": "Carregamento",
    "nome": "Carregador Portátil 5000Mah Sem fio Para iPhone Indução Bateria Carga",
    "preco": "28,88",
    "imagem": "https://cf.shopee.com.br/file/br-11134207-7r98o-mavkx3k4v9n308",
    "link": "https://s.shopee.com.br/8fQeoxvsZB"
  },
  {
    "cat": "Carregamento",
    "nome": "Bateria Portátil MagSafe 5000 10000mAh Carregamento Rápido 15W Sem Fio para iPhone",
    "preco": "52,00",
    "imagem": "https://cf.shopee.com.br/file/sg-11134201-821f9-mh293m88gi6j35",
    "link": "https://s.shopee.com.br/9AMvPstyYI"
  },
  {
    "cat": "Carregamento",
    "nome": "Power bank cabo incluso 5000/10000 mAh portátil lanterna",
    "preco": "40,90",
    "imagem": "https://cf.shopee.com.br/file/br-11134207-81ztc-mivl7lqhucjle4",
    "link": "https://s.shopee.com.br/903VDZubtH"
  },
  {
    "cat": "Periféricos",
    "nome": "MousePad Grande Caramelo Desk Pad Couro Gamer Office",
    "preco": "20,90",
    "imagem": "https://cf.shopee.com.br/file/sg-11134201-8261k-mmdczcdp0oaqd5",
    "link": "https://s.shopee.com.br/5LACqqHRAD"
  },
  {
    "cat": "Periféricos",
    "nome": "Mousepad Gamer TGT K50M, Grande, 500x500x3mm, Preto, TGT-K50M-GRB01",
    "preco": "40,09",
    "imagem": "https://cf.shopee.com.br/file/br-11134207-820m8-mqeqor4mw7i82d",
    "link": "https://s.shopee.com.br/5q6TRlFX9K"
  },
  {
    "cat": "Periféricos",
    "nome": "MousePad Grande Rosa Desk Pad Couro Gamer Office",
    "preco": "20,90",
    "imagem": "https://cf.shopee.com.br/file/sg-11134201-82602-mmdcdzfop4oy2e",
    "link": "https://s.shopee.com.br/5fn3FSGAUJ"
  },
  {
    "cat": "Periféricos",
    "nome": "Kit Mobilador Completo Teclado Mouse Gamer Rgb Mouse Pad Hub Tipo c Tripe",
    "preco": "63,99",
    "imagem": "https://cf.shopee.com.br/file/br-11134207-820le-mnwytrtoaeis3d",
    "link": "https://s.shopee.com.br/4qDwFvJLBA"
  },
  {
    "cat": "Periféricos",
    "nome": "Teclado Mecanico TGT Sherman V3 C1, Rainbow, ABNT2, Switch Vermelho, Preto, TGT-SHRC-RD01",
    "preco": "85,09",
    "imagem": "https://cf.shopee.com.br/file/br-11134207-820ls-mqeqor4mxm2o65",
    "link": "https://s.shopee.com.br/BS6hLoEml"
  },
  {
    "cat": "Periféricos",
    "nome": "Calculadora Colorida Morandi 12 Dígitos com Teclado Mecânico p/ Escola e Escritório Multineos",
    "preco": "22,99",
    "imagem": "https://cf.shopee.com.br/file/sg-11134201-7rdvq-lygm4gdp8dis3d",
    "link": "https://s.shopee.com.br/2LWbHKfzOC"
  },
  {
    "cat": "Periféricos",
    "nome": "Teclado Mecanico TGT Sherman V3 C1, Rainbow, ABNT2, Switch Marrom, Preto, TGT-SHRC-BR01",
    "preco": "82,40",
    "imagem": "https://cf.shopee.com.br/file/br-11134207-820l7-mqeqor4n0f7k82",
    "link": "https://s.shopee.com.br/2Vq1TdfM3F"
  },
  {
    "cat": "Periféricos",
    "nome": "Teclado Gamer Semi-Mecânico USB Iluminação LED RGB Rainbow Anti-Ghosting Resistente a Agua ABNT2",
    "preco": "39,97",
    "imagem": "https://cf.shopee.com.br/file/br-11134207-820lx-mp1n7p6463nq79",
    "link": "https://s.shopee.com.br/20tksihG4A"
  },
  {
    "cat": "Setup",
    "nome": "Base para suporte de laptop, adequada para laptops e tablets, feita de liga de alumínio, dobrável e portátil.",
    "preco": "20,90",
    "imagem": "https://cf.shopee.com.br/file/sg-11134201-824h1-mpjpmfa9962z18",
    "link": "https://s.shopee.com.br/1qaKgPqlGR"
  },
  {
    "cat": "Setup",
    "nome": "Mesa Portátil Multiuso Para Notebook Tablet Home Office Estudo Sala Cama Com Porta-Copo",
    "preco": "35,97",
    "imagem": "https://cf.shopee.com.br/file/br-11134207-81ztv-ml5ft6im9v5zfb",
    "link": "https://s.shopee.com.br/gONIGvCdE"
  },
  {
    "cat": "Setup",
    "nome": "Laptop Stand - Suporte para Notebook Dobrável de Ferro",
    "preco": "12,59",
    "imagem": "https://cf.shopee.com.br/file/sg-11134201-7rati-maedvjf4i6tf62",
    "link": "https://s.shopee.com.br/qhnUZuZIH"
  },
  {
    "cat": "Setup",
    "nome": "Suporte Dobrável para Notebook e Tablet | Base Plástica Portátil 7 Níveis de Ajuste Prático",
    "preco": "12,49",
    "imagem": "https://cf.shopee.com.br/file/br-11134207-820mg-mm22jene172803",
    "link": "https://s.shopee.com.br/111DgstvxK"
  },
  {
    "cat": "Iluminação",
    "nome": "Fita LED RGB 3528 5m 300 Leds com Controle Decoração Casa Loja Gesso Teto Sanca Vitrine",
    "preco": "10,99",
    "imagem": "https://cf.shopee.com.br/file/sg-11134201-7rbks-lnuai947xors77",
    "link": "https://s.shopee.com.br/7KvHEWj1O7"
  },
  {
    "cat": "Iluminação",
    "nome": "Fita Led Rgb 3528 Colorida 5m + Controle+Fonte 300 Led Decoração Casa Loja Gesso Teto Sanca Vitrine",
    "preco": "21,98",
    "imagem": "https://cf.shopee.com.br/file/cn-11134207-820l4-mlerf1o7louga0",
    "link": "https://s.shopee.com.br/7Abr2Djej6"
  },
  {
    "cat": "Iluminação",
    "nome": "Fita LED USB RGB-SMD 5050/2835 Flexível Para Decoração De Quarto E",
    "preco": "10,27",
    "imagem": "https://cf.shopee.com.br/file/sg-11134201-823og-mp4mt4ms2ivg72",
    "link": "https://s.shopee.com.br/70IQpukI45"
  },
  {
    "cat": "Iluminação",
    "nome": "Fita De Led 5M USB Siliconada 6W Rgb Colorido  5 M/3M/2M  Com Controle Remoto 5V",
    "preco": "15,99",
    "imagem": "https://cf.shopee.com.br/file/br-11134207-820m5-moicsrqvii9vda",
    "link": "https://s.shopee.com.br/6pz0dbkvP4"
  },
  {
    "cat": "Vestível",
    "nome": "Smartwatch D20 - Relógio Inteligente y68 Esportivo Bluetooth Android/iOS - Com foto Na Tela",
    "preco": "19,97",
    "imagem": "https://cf.shopee.com.br/file/sg-11134201-7rffl-m43c8kw5s9cv7e",
    "link": "https://s.shopee.com.br/8pk51HqIsU"
  },
  {
    "cat": "Vestível",
    "nome": "2025 Nova Série 8 Relógio T800 Ultra Smart Watch Esportivo Sem Fio À Prova D'água T800 Ultra2 MAX",
    "preco": "38,88",
    "imagem": "https://cf.shopee.com.br/file/sg-11134201-7rdym-lxrzfhio6fhl9d",
    "link": "https://s.shopee.com.br/8fQeoyqwDT"
  },
  {
    "cat": "Vestível",
    "nome": "2026 Novo S10 Mais Recente Smartwatch Relógio Inteligente Série Ultra NFC Sem Carregamento",
    "preco": "59,90",
    "imagem": "https://cf.shopee.com.br/file/br-11134207-820lr-mpsq0fxxea6bee",
    "link": "https://s.shopee.com.br/8V7EcfrZYS"
  },
  {
    "cat": "Vestível",
    "nome": "Pulseira de silicone para Smartwatch 44mm 40mm 38mm 42mm cinto de borracha smartwatch pulseira iwatch",
    "preco": "7,99",
    "imagem": "https://cf.shopee.com.br/file/b1ed91ed9ff02a3b583b6891da086210",
    "link": "https://s.shopee.com.br/8KnoQMsCtR"
  }
]